ievm/__init__.py
ievm/__main__.py
ievm-0.0.1.dist-info/LICENSE.txt
ievm-0.0.1.dist-info/METADATA
ievm-0.0.1.dist-info/RECORD
ievm-0.0.1.dist-info/WHEEL
ievm-0.0.1.dist-info/entry_points.txt
ievm-0.0.1.dist-info/top_level.txt
