Metadata-Version: 2.1
Name: ievm
Version: 0.0.1
Summary: tool for downloading IE VMs with checksum
Home-page: https://github.com/zenixls2/ievm
Author: Zenix Huang
Author-email: zenixls2@gmail.com
License: Apache License 2.0
Keywords: ie vm InternetExplore
Platform: UNKNOWN
Classifier: Development Status :: 5 - Production/Stable
Classifier: Environment :: Console
Classifier: Environment :: Web Environment
Classifier: Intended Audience :: Developers
Classifier: Intended Audience :: System Administrators
Classifier: License :: OSI Approved :: Apache Software License
Classifier: Programming Language :: Python :: 2.7
Classifier: Programming Language :: Python :: 3.3
Classifier: Programming Language :: Python :: 3.4
Classifier: Programming Language :: Python :: 3.5
Classifier: Programming Language :: Python :: 3.6
Classifier: Topic :: System :: Monitoring
Classifier: Topic :: Internet
Classifier: Topic :: Utilities
Requires-Dist: requests
